MANIFEST.in
README.rst
setup.py
django_providerregistry.egg-info/PKG-INFO
django_providerregistry.egg-info/SOURCES.txt
django_providerregistry.egg-info/dependency_links.txt
django_providerregistry.egg-info/requires.txt
django_providerregistry.egg-info/top_level.txt
providerregistry/__init__.py
providerregistry/admin.py
providerregistry/forms.py
providerregistry/models.py
providerregistry/urls.py
providerregistry/utils.py
providerregistry/views.py
providerregistry/static/providerregistry/img/Female250.jpg
providerregistry/static/providerregistry/img/Male250.jpg
providerregistry/static/providerregistry/img/Organization250.jpg
providerregistry/static/providerregistry/img/favicon.png
providerregistry/static/providerregistry/modern-business/bin/contact_me.php
providerregistry/static/providerregistry/modern-business/css/bootstrap.css
providerregistry/static/providerregistry/modern-business/css/bootstrap.min.css
providerregistry/static/providerregistry/modern-business/css/modern-business.css
providerregistry/static/providerregistry/modern-business/font-awesome-4.1.0/css/font-awesome.css
providerregistry/static/providerregistry/modern-business/font-awesome-4.1.0/css/font-awesome.min.css
providerregistry/static/providerregistry/modern-business/font-awesome-4.1.0/fonts/FontAwesome.otf
providerregistry/static/providerregistry/modern-business/font-awesome-4.1.0/fonts/fontawesome-webfont.eot
providerregistry/static/providerregistry/modern-business/font-awesome-4.1.0/fonts/fontawesome-webfont.svg
providerregistry/static/providerregistry/modern-business/font-awesome-4.1.0/fonts/fontawesome-webfont.ttf
providerregistry/static/providerregistry/modern-business/font-awesome-4.1.0/fonts/fontawesome-webfont.woff
providerregistry/static/providerregistry/modern-business/font-awesome-4.1.0/less/bordered-pulled.less
providerregistry/static/providerregistry/modern-business/font-awesome-4.1.0/less/core.less
providerregistry/static/providerregistry/modern-business/font-awesome-4.1.0/less/fixed-width.less
providerregistry/static/providerregistry/modern-business/font-awesome-4.1.0/less/font-awesome.less
providerregistry/static/providerregistry/modern-business/font-awesome-4.1.0/less/icons.less
