Metadata-Version: 1.1
Name: django-providerregistry
Version: 0.6.0
Summary: A simple Django application that provides a UI and RESTFul API for read only access to NPPES data.
Home-page: https://github.com/hhsidealab/django-providerregistry
Author: Alan Viars
Author-email: sales@videntity.com
License: Public Domain
Platform: UNKNOWN
Classifier: Environment :: Web Environment
Classifier: Framework :: Django
Classifier: Intended Audience :: Developers
Classifier: Operating System :: OS Independent
Classifier: Programming Language :: Python
Classifier: Programming Language :: Python :: 2.7
Classifier: Topic :: Internet :: WWW/HTTP
Classifier: Topic :: Internet :: WWW/HTTP :: Dynamic Content
